{
    "job_reference": "REF. NUM: 248978",
    "job_description": "Epic is one of the largest telecommunications companies in Cyprus and a member of a dynamic European family of telecommunications companies. With ability, innovation and agility at our core, we are offering a state-of-the-art network recognized by multiple awards in Cyprus.\nAt Epic we take care of our people and we enhance a people centric and learning culture for your professional growth. We are always looking for ambitious employees to be a part of our award-winning organisation!\nOur team is growing so join us to take your career to the next level and become a part of our team of more than 350 professionals.\nThe role:\nWe are looking for a motivated Trainee Store Supervisor to be based in Limassol. The main responsibility of the role will be to provide quality customer service and support to subscribers and prospective clients, themselves and by leading a sales team. Furthermore, promote products and services of the Company in a favorable manner.\nYour Responsibilities:\nLiaising between the Management and other employeesTraining new store employeesDeveloping training materials and conducting training sessions and workshopsEstablishing business knowledge and awareness of shared company goalsMonitoring both individual and team job performance metricsProviding staff with Sales guidance and assistanceRelaying productivity concerns to the ManagementPreparing job descriptions and work schedulesAssisting with other administrative tasks, when requiredLead the team to achieve pre-established objectives. Reach sales targetsFollow-up representatives’ results by taking appropriate corrective actionMaintain POS premises and assetsTake immediate action on urgent needs of all shops in area for smooth operation of shops and consistent service to external customers Assist in developing and implementing POS sales strategyFollow up difficult cases and insure their resolution in the most efficient mannerEnsure appropriate preventive and corrective action to maintain standards of quality and subscriber or prospective client satisfactionMaintain stock levels according to company’s policyTake corrective actions for cash shortages/surplus\nLiaising between the Management and other employees\nTraining new store employees\nDeveloping training materials and conducting training sessions and workshops\nEstablishing business knowledge and awareness of shared company goals\nMonitoring both individual and team job performance metrics\nProviding staff with Sales guidance and assistance\nRelaying productivity concerns to the Management\nPreparing job descriptions and work schedules\nAssisting with other administrative tasks, when required\nLead the team to achieve pre-established objectives. Reach sales targets\nFollow-up representatives’ results by taking appropriate corrective action\nMaintain POS premises and assets\nTake immediate action on urgent needs of all shops in area for smooth operation of shops and consistent service to external customers\nAssist in developing and implementing POS sales strategy\nFollow up difficult cases and insure their resolution in the most efficient manner\nEnsure appropriate preventive and corrective action to maintain standards of quality and subscriber or prospective client satisfaction\nMaintain stock levels according to company’s policy\nTake corrective actions for cash shortages/surplus\nOur proposition:\nCompetitive remuneration package€200 living allowanceStimulating monthly bonus13th salaryAttractive benefits with comprehensive medical and life insurances and provident fundCompany telecom products with free mobile and internet lines and exclusive discounts for our services with maximum monthly total value of 120 euros Opportunity for a sustainable career and continuously building skills and expertise in a dynamic technology sector\nCompetitive remuneration package\n€200 living allowance\nStimulating monthly bonus\n13th salary\nAttractive benefits with comprehensive medical and life insurances and provident fund\nCompany telecom products with free mobile and internet lines and exclusive discounts for our services with maximum monthly total value of 120 euros\nOpportunity for a sustainable career and continuously building skills and expertise in a dynamic technology sector\nYour Profile:\nMinimum 2 years of experience in Retail sales environment, ideally within an IT or Technology environment. Proven experience as a team leader or Supervisor will be considered as an advantageUniversity Degree or College Diploma (Business Management, Marketing, Social or Economic studies) will be considered as advantageExperience with direct reports will be considered as an advantageExceptional leadership potential with the ability to work well with others in a motivational mannerBasic knowledge of GSM technology and servicesClear communication skills, and the ability to relate to different peopleFluent in English and Greek. Russian language will be considered an asset\nMinimum 2 years of experience in Retail sales environment, ideally within an IT or Technology environment. Proven experience as a team leader or Supervisor will be considered as an advantage\nUniversity Degree or College Diploma (Business Management, Marketing, Social or Economic studies) will be considered as advantage\nExperience with direct reports will be considered as an advantage\nExceptional leadership potential with the ability to work well with others in a motivational manner\nBasic knowledge of GSM technology and services\nClear communication skills, and the ability to relate to different people\nFluent in English and Greek. Russian language will be considered an asset\nInterested to join a team of passionate professionals? Apply now! Send your CV to career@epic.com.cy stating the job title in the subject line.\n",
    "industry": {
        "industry_name": "Telecommunications",
        "NACE_industry_name": "G. Information and Communication"
    },
    "The role": "Trainee Store Supervisor",
    "Your Responsibilities": [
        "Liaising between the Management and other employees",
        "Training new store employees",
        "Developing training materials and conducting training sessions and workshops",
        "Establishing business knowledge and awareness of shared company goals",
        "Monitoring both individual and team job performance metrics",
        "Providing staff with Sales guidance and assistance",
        "Relaying productivity concerns to the Management",
        "Preparing job descriptions and work schedules",
        "Assisting with other administrative tasks, when required",
        "Lead the team to achieve pre-established objectives. Reach sales targets",
        "Follow-up representatives’ results by taking appropriate corrective action",
        "Maintain POS premises and assets",
        "Take immediate action on urgent needs of all shops in area for smooth operation of shops and consistent service to external customers",
        "Assist in developing and implementing POS sales strategy",
        "Follow up difficult cases and insure their resolution in the most efficient manner",
        "Ensure appropriate preventive and corrective action to maintain standards of quality and subscriber or prospective client satisfaction",
        "Maintain stock levels according to company’s policy",
        "Take corrective actions for cash shortages/surplus"
    ],
    "Our proposition": [
        "Competitive remuneration package",
        "€200 living allowance",
        "Stimulating monthly bonus",
        "13th salary",
        "Attractive benefits with comprehensive medical and life insurances and provident fund",
        "Company telecom products with free mobile and internet lines and exclusive discounts for our services with maximum monthly total value of 120 euros",
        "Opportunity for a sustainable career and continuously building skills and expertise in a dynamic technology sector"
    ],
    "Your Profile": [
        "Minimum 2 years of experience in Retail sales environment, ideally within an IT or Technology environment.",
        "Proven experience as a team leader or Supervisor will be considered as an advantage",
        "University Degree or College Diploma (Business Management, Marketing, Social or Economic studies) will be considered as advantage",
        "Experience with direct reports will be considered as an advantage",
        "Exceptional leadership potential with the ability to work well with others in a motivational manner",
        "Basic knowledge of GSM technology and services",
        "Clear communication skills, and the ability to relate to different people",
        "Fluent in English and Greek. Russian language will be considered an asset"
    ],
    "skills": [
        {
            "skills_category": "Soft Skill",
            "skills_name": "Leadership",
            "skills_type": "Personality Trait"
        },
        {
            "skills_category": "Soft Skill",
            "skills_name": "Communication",
            "skills_type": "Personality Trait"
        },
        {
            "skills_category": "Hard Skill",
            "skills_name": "Training",
            "skills_type": "Professional"
        },
        {
            "skills_category": "Hard Skill",
            "skills_name": "Customer Service",
            "skills_type": "Technical skills"
        },
        {
            "skills_category": "Soft Skill",
            "skills_name": "Teamwork",
            "skills_type": "Personality Trait"
        },
        {
            "skills_category": "Hard Skill",
            "skills_name": "Time Management",
            "skills_type": "Professional"
        }
    ],
    "certification_degree": [
        {},
        {}
    ],
    "academic_degree": [
        {
            "academic_degree_name": "University Degree or College Diploma",
            "academic_degree_field": [
                "Business Management",
                "Marketing",
                "Social or Economic studies"
            ]
        }
    ],
    "experience": {
        "experience_required": true,
        "years_of_experience": 2
    },
    "benefits": [
        {
            "benefit_name": "Competitive remuneration package"
        },
        {
            "benefit_name": "€200 living allowance"
        },
        {
            "benefit_name": "Stimulating monthly bonus"
        },
        {
            "benefit_name": "13th salary"
        },
        {
            "benefit_name": "Attractive benefits with comprehensive medical and life insurances and provident fund"
        },
        {
            "benefit_name": "Company telecom products with free mobile and internet lines and exclusive discounts for our services with maximum monthly total value of 120 euros"
        },
        {
            "benefit_name": "Opportunity for a sustainable career and continuously building skills and expertise in a dynamic technology sector"
        }
    ],
    "responsibilities": [
        {
            "responsibility_name": "Liaising between the Management and other employees"
        },
        {
            "responsibility_name": "Training new store employees"
        },
        {
            "responsibility_name": "Developing training materials and conducting training sessions and workshops"
        },
        {
            "responsibility_name": "Establishing business knowledge and awareness of shared company goals"
        },
        {
            "responsibility_name": "Monitoring both individual and team job performance metrics"
        },
        {
            "responsibility_name": "Providing staff with Sales guidance and assistance"
        },
        {
            "responsibility_name": "Relaying productivity concerns to the Management"
        },
        {
            "responsibility_name": "Preparing job descriptions and work schedules"
        },
        {
            "responsibility_name": "Assisting with other administrative tasks, when required"
        },
        {
            "responsibility_name": "Lead the team to achieve pre-established objectives. Reach sales targets"
        },
        {
            "responsibility_name": "Follow-up representatives’ results by taking appropriate corrective action"
        },
        {
            "responsibility_name": "Maintain POS premises and assets"
        },
        {
            "responsibility_name": "Take immediate action on urgent needs of all shops in area for smooth operation of shops and consistent service to external customers"
        },
        {
            "responsibility_name": "Assist in developing and implementing POS sales strategy"
        },
        {
            "responsibility_name": "Follow up difficult cases and insure their resolution in the most efficient manner"
        },
        {
            "responsibility_name": "Ensure appropriate preventive and corrective action to maintain standards of quality and subscriber or prospective client satisfaction"
        },
        {
            "responsibility_name": "Maintain stock levels according to company’s policy"
        },
        {
            "responsibility_name": "Take corrective actions for cash shortages/surplus"
        }
    ]
}